iree/tf/support/__init__.py
iree/tf/support/module_utils.py
iree/tf/support/module_utils_test.py
iree/tf/support/tf_test_utils.py
iree/tf/support/tf_test_utils_test.py
iree/tf/support/tf_utils.py
iree/tf/support/tf_utils_test.py
iree/tf/support/trace_utils.py
iree/tf/support/trace_utils_test.py
iree/tools/tf/__init__.py
iree/tools/tf/scripts/iree_import_tf/__main__.py
iree_tools_tf-20251010.1410.dist-info/METADATA
iree_tools_tf-20251010.1410.dist-info/WHEEL
iree_tools_tf-20251010.1410.dist-info/entry_points.txt
iree_tools_tf-20251010.1410.dist-info/top_level.txt
iree_tools_tf-20251010.1410.dist-info/RECORD
